weeby/__init__.py
weeby/config.py
weeby/effects.py
weeby/generators.py
weeby/json_response.py
weeby/media.py
weeby/overlays.py
weeby/util.py
weeby.py-0.1.6.dist-info/LICENSE
weeby.py-0.1.6.dist-info/METADATA
weeby.py-0.1.6.dist-info/WHEEL
weeby.py-0.1.6.dist-info/top_level.txt
weeby.py-0.1.6.dist-info/RECORD
