Metadata-Version: 2.1
Name: weeby.py
Version: 0.1.6
Summary: API wrapper library for WeebyAPI
Home-page: UNKNOWN
Author: Ashish Bhushan
Author-email: asheeshh9@gmail.com
License: UNKNOWN
Project-URL: Homepage, https://github.com/asheeeshh/weeby.py
Platform: UNKNOWN
Classifier: Intended Audience :: Developers
Classifier: Programming Language :: Python :: 3
Classifier: License :: OSI Approved :: MIT License
Classifier: Operating System :: OS Independent
Requires-Dist: requests
